dffr/__init__.py
dffr/utils.py
tests/__init__.py
tests/test_utils.py
dffr-0.0.2.dist-info/LICENSE
dffr-0.0.2.dist-info/METADATA
dffr-0.0.2.dist-info/WHEEL
dffr-0.0.2.dist-info/top_level.txt
dffr-0.0.2.dist-info/RECORD
