Metadata-Version: 2.1
Name: dffr
Version: 0.0.2
Summary: Find a difference between two mutable Python types.
Home-page: https://github.com/vald-phoenix/dffr
Author: Vladyslav Krylasov
Author-email: vladyslav.krylasov@gmail.com
License: UNKNOWN
Platform: UNKNOWN
Classifier: Programming Language :: Python :: 3
Classifier: License :: OSI Approved :: MIT License
Classifier: Operating System :: OS Independent
